<?xml version="1.0" encoding="utf-8"?>
<Ragdoll type="Voidleviathan" texture="%ModDir%/Characters/ExtendedMonsterCreatures/Voidleviathan/Voidleviathan.png" canentersubmarine="True" canwalk="False" spritesheetorientation="0" limbscale="2" jointscale="2" texturescale="1" colliderheightfromfloor="45" impacttolerance="50" draggable="True" mainlimb="Torso" color="255,255,255,255">
  <collider radius="302" width="1" name="Main Collider" height="680" />
  <limb id="0" name="Limb 0" type="Torso" height="724.19995" width="0" notes="" spriteorientation="NaN" flip="True" mirrorvertically="False" mirrorhorizontally="False" hide="False" attackpriority="1" steerforce="0" radius="240" density="10" ignorecollisions="False" angulardamping="7" pullpos="0,0" stepoffset="0,0" refjoint="-1" mouthpos="0,0" constanttorque="0" constantangle="0" scale="1" attackforcemultiplier="1" minseverancedamage="1" healthindex="0" friction="0.3" restitution="0.05" severedfadeouttime="10" applytailangle="False" sinefrequencymultiplier="1" sineamplitudemultiplier="1" blinkfrequency="0" blinkdurationin="0.2" blinkdurationout="0.5" blinkholdtime="0" blinkrotationin="0" blinkrotationout="45" blinkforce="50" blinktransitionin="Linear" blinktransitionout="Linear" inheritlimbdepth="None" onlyblinkinwater="False">
    <deformablesprite texture="" sourcerect="1441,609,605,852" origin="0.5,0.5" depth="0" color="255,255,255,255" deadcolor="255,255,255,255" deadcolortime="0" subdivisions="5,5" ignoretint="False">
      <spritedeformation type="bendjoint" resolution="5,5" maxrotation="20" sync="-1" typename="bendjoint" blendmode="Add" strength="2" usemovementsine="False" stopwhenhostisdead="False" sineoffset="0" onlyinwater="False" />
    </deformablesprite>
    <damagemodifier damagesound="" damagemultiplier="0.8" probabilitymultiplier="1" armorsector="0,360" deflectprojectiles="False" afflictionidentifiers="" afflictiontypes="" damageparticle="" />
  </limb>
  <limb id="1" name="Limb 1" type="Head" height="0" width="0" notes="" spriteorientation="NaN" flip="True" mirrorvertically="False" mirrorhorizontally="False" hide="False" attackpriority="1" steerforce="25" radius="250" density="10" ignorecollisions="False" angulardamping="7" pullpos="0,0" stepoffset="0,0" refjoint="-1" mouthpos="0,0" constanttorque="0" constantangle="0" scale="1" attackforcemultiplier="1" minseverancedamage="1" healthindex="0" friction="0.3" restitution="0.05" severedfadeouttime="10" applytailangle="False" sinefrequencymultiplier="1" sineamplitudemultiplier="1" blinkfrequency="0" blinkdurationin="0.2" blinkdurationout="0.5" blinkholdtime="0" blinkrotationin="0" blinkrotationout="45" blinkforce="50" blinktransitionin="Linear" blinktransitionout="Linear" inheritlimbdepth="None" onlyblinkinwater="False">
    <deformablesprite texture="" sourcerect="1442,107,604,511" origin="0.5,0.5" depth="0" color="255,255,255,255" deadcolor="255,255,255,255" deadcolortime="0" subdivisions="5,5" ignoretint="False">
      <spritedeformation type="bendjoint" resolution="5,5" maxrotation="20" sync="-1" typename="bendjoint" blendmode="Add" strength="2" usemovementsine="False" stopwhenhostisdead="False" sineoffset="0" onlyinwater="False" />
    </deformablesprite>
    <attack structuresoundtype="StructureBlunt" context="Any" targettype="Any" targetlimbtype="None" hitdetectiontype="Distance" afterattack="FallBackUntilCanAttack" afterattackdelay="0" reverse="False" retreat="False" range="700" damagerange="700" duration="0.25" cooldown="12" secondarycooldown="0" cooldownrandomfactor="0" structuredamage="100" itemdamage="120" stun="0" onlyhumans="False" applyforceonlimbs="" force="31.700085" rootforceworldstart="0,0" rootforceworldmiddle="0,0" rootforceworldend="0,0" roottransitioneasing="Linear" torque="0" applyforcesonlyonce="False" targetimpulse="800" targetimpulseworld="0,0" targetforce="0" targetforceworld="0,0" severlimbsprobability="0" priority="0" fullspeedafterattack="False" penetration="0" levelwalldamage="500" ranged="False" avoidfriendlyfire="False" requiredangle="20" submarineimpactmultiplier="1" blink="False">
      <StatusEffect type="OnUse" target="NearbyCharacters">
        <Explosion ignorecover="true" onlyinside="true" range="2000" force="20" flames="false" shockwave="false" sparks="false" flash="false" underwaterbubble="false" camerashake="1000" playtinnitus="false" structuredamage="30" applyFireEffects="false">
          <Conditional speciesname="human" />
          <Conditional speciesname="!eq voidleviathan" />
          <Affliction identifier="stun" strength="0.5" probability="1" />
          <affliction identifier="lacerations" strength="10" probability="1" />
          <affliction identifier="bleeding" strength="20" probability="1" />
          <ParticleEmitter particle="shrapnel" drawontop="True" particleamount="50" scalemin="5" scalemax="5" velocitymin="0" velocitymax="20" anglemin="0" anglemax="360" />
          <ParticleEmitter particle="shrapnel" drawontop="True" particleamount="50" scalemin="5" scalemax="5" velocitymin="0" velocitymax="20" anglemin="0" anglemax="360" />
        </Explosion>
      </StatusEffect>
      <affliction identifier="bitewounds" strength="90" probability="1" />
      <affliction identifier="consumed" strength="100" probability="1" />
    </attack>
    <damagemodifier damagesound="" damagemultiplier="1" probabilitymultiplier="1" armorsector="0,360" deflectprojectiles="False" afflictionidentifiers="" afflictiontypes="" damageparticle="" />
    <damagemodifier damagesound="" damagemultiplier="0.8" probabilitymultiplier="0.5" armorsector="0,360" deflectprojectiles="False" afflictionidentifiers="" afflictiontypes="damage" damageparticle="" />
  </limb>
  <limb id="2" radius="220" width="415.65" height="710.6" name="Limb 2" type="None" spriteorientation="NaN" flip="True" mirrorvertically="False" mirrorhorizontally="False" hide="False" attackpriority="1" steerforce="0" density="10" ignorecollisions="False" angulardamping="7" pullpos="0,0" stepoffset="0,0" refjoint="-1" mouthpos="0,0" notes="" constanttorque="0" constantangle="0" scale="1" attackforcemultiplier="1" minseverancedamage="1" healthindex="0" friction="0.3" restitution="0.05" severedfadeouttime="10" applytailangle="False" sinefrequencymultiplier="1" sineamplitudemultiplier="1" blinkfrequency="0" blinkdurationin="0.2" blinkdurationout="0.5" blinkholdtime="0" blinkrotationin="0" blinkrotationout="45" blinkforce="50" blinktransitionin="Linear" blinktransitionout="Linear" inheritlimbdepth="None" onlyblinkinwater="False">
    <deformablesprite texture="" sourcerect="1473,1454,489,836" origin="0.5,0.5" depth="0" color="255,255,255,255" deadcolor="255,255,255,255" deadcolortime="0" subdivisions="5,5" ignoretint="False">
      <spritedeformation type="bendjoint" resolution="5,5" maxrotation="20" sync="-1" typename="bendjoint" blendmode="Add" strength="2" usemovementsine="False" stopwhenhostisdead="False" sineoffset="0" onlyinwater="False" />
    </deformablesprite>
    <damagemodifier damagesound="" damagemultiplier="0.7" probabilitymultiplier="1" armorsector="0,360" deflectprojectiles="False" afflictionidentifiers="" afflictiontypes="" damageparticle="" />
  </limb>
  <limb id="3" radius="110" width="413.95" height="532.10004" name="Limb 3" type="Tail" spriteorientation="NaN" flip="True" mirrorvertically="False" mirrorhorizontally="False" hide="False" attackpriority="1" steerforce="0" density="10" ignorecollisions="False" angulardamping="7" pullpos="0,0" stepoffset="0,0" refjoint="-1" mouthpos="0,0" notes="" constanttorque="0" constantangle="0" scale="1" attackforcemultiplier="1" minseverancedamage="1" healthindex="0" friction="0.3" restitution="0.05" severedfadeouttime="10" applytailangle="False" sinefrequencymultiplier="1" sineamplitudemultiplier="1" blinkfrequency="0" blinkdurationin="0.2" blinkdurationout="0.5" blinkholdtime="0" blinkrotationin="0" blinkrotationout="45" blinkforce="50" blinktransitionin="Linear" blinktransitionout="Linear" inheritlimbdepth="None" onlyblinkinwater="False">
    <deformablesprite texture="" sourcerect="1475,2279,487,626" origin="0.5,0.5" depth="0" color="255,255,255,255" deadcolor="255,255,255,255" deadcolortime="0" subdivisions="5,5" ignoretint="False">
      <spritedeformation type="bendjoint" resolution="5,5" maxrotation="20" sync="-1" typename="bendjoint" blendmode="Add" strength="2" usemovementsine="False" stopwhenhostisdead="False" sineoffset="0" onlyinwater="False" />
    </deformablesprite>
    <damagemodifier damagesound="" damagemultiplier="0.6" probabilitymultiplier="1" armorsector="0,360" deflectprojectiles="False" afflictionidentifiers="" afflictiontypes="" damageparticle="" />
  </limb>
  <limb id="4" radius="60" width="413.95" height="641.75" name="Limb 4" type="None" spriteorientation="NaN" flip="True" mirrorvertically="False" mirrorhorizontally="False" hide="False" attackpriority="1" steerforce="0" density="10" ignorecollisions="False" angulardamping="7" pullpos="0,0" stepoffset="0,0" refjoint="-1" mouthpos="0,0" notes="" constanttorque="0" constantangle="0" scale="1" attackforcemultiplier="1" minseverancedamage="1" healthindex="0" friction="0.3" restitution="0.05" severedfadeouttime="10" applytailangle="False" sinefrequencymultiplier="1" sineamplitudemultiplier="1" blinkfrequency="0" blinkdurationin="0.2" blinkdurationout="0.5" blinkholdtime="0" blinkrotationin="0" blinkrotationout="45" blinkforce="50" blinktransitionin="Linear" blinktransitionout="Linear" inheritlimbdepth="None" onlyblinkinwater="False">
    <deformablesprite texture="" sourcerect="1475,2890,487,755" origin="0.5,0.5" depth="0" color="255,255,255,255" deadcolor="255,255,255,255" deadcolortime="0" subdivisions="5,5" ignoretint="False">
      <spritedeformation type="bendjoint" resolution="5,5" maxrotation="20" sync="-1" typename="bendjoint" blendmode="Add" strength="2" usemovementsine="False" stopwhenhostisdead="False" sineoffset="0" onlyinwater="False" />
    </deformablesprite>
    <damagemodifier damagesound="" damagemultiplier="0.3" probabilitymultiplier="1" armorsector="0,360" deflectprojectiles="False" afflictionidentifiers="" afflictiontypes="" damageparticle="" />
  </limb>
  <limb id="5" width="206.55" height="300.05" name="Limb 5" type="None" spriteorientation="NaN" flip="True" mirrorvertically="False" mirrorhorizontally="False" hide="False" attackpriority="1" steerforce="0" radius="70" density="10" ignorecollisions="False" angulardamping="7" pullpos="0,0" stepoffset="0,0" refjoint="-1" mouthpos="0,0" notes="" constanttorque="0" constantangle="0" scale="1" attackforcemultiplier="1" minseverancedamage="1" healthindex="0" friction="0.3" restitution="0.05" severedfadeouttime="10" applytailangle="False" sinefrequencymultiplier="1" sineamplitudemultiplier="1" blinkfrequency="0" blinkdurationin="0.2" blinkdurationout="0.5" blinkholdtime="0" blinkrotationin="0" blinkrotationout="45" blinkforce="50" blinktransitionin="Linear" blinktransitionout="Linear" inheritlimbdepth="None" onlyblinkinwater="False">
    <deformablesprite texture="" sourcerect="541,333,243,353" origin="0.5,0.5" depth="0.05" color="255,255,255,255" deadcolor="255,255,255,255" deadcolortime="0" subdivisions="5,5" ignoretint="False"></deformablesprite>
    <damagemodifier damagesound="" damagemultiplier="0.3" probabilitymultiplier="1" armorsector="0,360" deflectprojectiles="False" afflictionidentifiers="" afflictiontypes="damage" damageparticle="" />
    <damagemodifier damagesound="" damagemultiplier="0.1" probabilitymultiplier="1" armorsector="0,360" deflectprojectiles="False" afflictionidentifiers="" afflictiontypes="bleeding" damageparticle="" />
  </limb>
  <limb id="6" radius="70" width="175.1" height="562.7" name="Limb 6" type="None" spriteorientation="NaN" flip="True" mirrorvertically="False" mirrorhorizontally="False" hide="False" attackpriority="1" steerforce="0" density="10" ignorecollisions="False" angulardamping="7" pullpos="0,0" stepoffset="0,0" refjoint="-1" mouthpos="0,0" notes="" constanttorque="0" constantangle="0" scale="1" attackforcemultiplier="1" minseverancedamage="1" healthindex="0" friction="0.3" restitution="0.05" severedfadeouttime="10" applytailangle="False" sinefrequencymultiplier="1" sineamplitudemultiplier="1" blinkfrequency="0" blinkdurationin="0.2" blinkdurationout="0.5" blinkholdtime="0" blinkrotationin="0" blinkrotationout="45" blinkforce="50" blinktransitionin="Linear" blinktransitionout="Linear" inheritlimbdepth="None" onlyblinkinwater="False">
    <deformablesprite texture="" sourcerect="541,678,206,662" origin="0.5,0.5" depth="0.05" color="255,255,255,255" deadcolor="255,255,255,255" deadcolortime="0" subdivisions="5,5" ignoretint="False">
      <spritedeformation type="bendjoint" resolution="5,5" maxrotation="20" sync="-1" typename="bendjoint" blendmode="Add" strength="2" usemovementsine="False" stopwhenhostisdead="False" sineoffset="0" onlyinwater="False" />
    </deformablesprite>
    <damagemodifier damagesound="" damagemultiplier="0.1" probabilitymultiplier="1" armorsector="0,360" deflectprojectiles="False" afflictionidentifiers="" afflictiontypes="bleeding" damageparticle="" />
    <damagemodifier damagesound="" damagemultiplier="0.3" probabilitymultiplier="1" armorsector="0,360" deflectprojectiles="False" afflictionidentifiers="" afflictiontypes="damage" damageparticle="" />
  </limb>
  <limb id="7" radius="60" width="175.1" height="357" name="Limb 7" type="None" spriteorientation="NaN" flip="True" mirrorvertically="False" mirrorhorizontally="False" hide="False" attackpriority="1" steerforce="0" density="10" ignorecollisions="False" angulardamping="7" pullpos="0,0" stepoffset="0,0" refjoint="-1" mouthpos="0,0" notes="" constanttorque="0" constantangle="0" scale="1" attackforcemultiplier="1" minseverancedamage="1" healthindex="0" friction="0.3" restitution="0.05" severedfadeouttime="10" applytailangle="False" sinefrequencymultiplier="1" sineamplitudemultiplier="1" blinkfrequency="0" blinkdurationin="0.2" blinkdurationout="0.5" blinkholdtime="0" blinkrotationin="0" blinkrotationout="45" blinkforce="50" blinktransitionin="Linear" blinktransitionout="Linear" inheritlimbdepth="None" onlyblinkinwater="False">
    <deformablesprite texture="" sourcerect="541,1336,206,420" origin="0.5,0.5" depth="0.05" color="255,255,255,255" deadcolor="255,255,255,255" deadcolortime="0" subdivisions="5,5" ignoretint="False">
      <spritedeformation type="bendjoint" resolution="5,5" maxrotation="20" sync="-1" typename="bendjoint" blendmode="Add" strength="2" usemovementsine="False" stopwhenhostisdead="False" sineoffset="0" onlyinwater="False" />
    </deformablesprite>
    <damagemodifier damagesound="" damagemultiplier="0.3" probabilitymultiplier="1" armorsector="0,360" deflectprojectiles="False" afflictionidentifiers="" afflictiontypes="damage" damageparticle="" />
    <damagemodifier damagesound="" damagemultiplier="0.1" probabilitymultiplier="1" armorsector="0,360" deflectprojectiles="False" afflictionidentifiers="" afflictiontypes="bleeding" damageparticle="" />
  </limb>
  <limb id="8" radius="50" width="175.1" height="437.75" name="Limb 8" type="None" spriteorientation="NaN" flip="True" mirrorvertically="False" mirrorhorizontally="False" hide="False" attackpriority="1" steerforce="0" density="10" ignorecollisions="False" angulardamping="7" pullpos="0,0" stepoffset="0,0" refjoint="-1" mouthpos="0,0" notes="" constanttorque="0" constantangle="0" scale="1" attackforcemultiplier="1" minseverancedamage="1" healthindex="0" friction="0.3" restitution="0.05" severedfadeouttime="10" applytailangle="False" sinefrequencymultiplier="1" sineamplitudemultiplier="1" blinkfrequency="0" blinkdurationin="0.2" blinkdurationout="0.5" blinkholdtime="0" blinkrotationin="0" blinkrotationout="45" blinkforce="50" blinktransitionin="Linear" blinktransitionout="Linear" inheritlimbdepth="None" onlyblinkinwater="False">
    <deformablesprite texture="" sourcerect="541,1749,206,515" origin="0.5,0.5" depth="0.05" color="255,255,255,255" deadcolor="255,255,255,255" deadcolortime="0" subdivisions="5,5" ignoretint="False">
      <spritedeformation type="bendjoint" resolution="5,5" maxrotation="20" sync="-1" typename="bendjoint" blendmode="Add" strength="2" usemovementsine="False" stopwhenhostisdead="False" sineoffset="0" onlyinwater="False" />
    </deformablesprite>
    <damagemodifier damagesound="" damagemultiplier="0.3" probabilitymultiplier="1" armorsector="0,360" deflectprojectiles="False" afflictionidentifiers="" afflictiontypes="" damageparticle="" />
    <damagemodifier damagesound="" damagemultiplier="0.1" probabilitymultiplier="1" armorsector="0,360" deflectprojectiles="False" afflictionidentifiers="" afflictiontypes="bleeding" damageparticle="" />
  </limb>
  <limb id="9" radius="70" width="201.45" height="345.1" name="Limb 9" type="None" spriteorientation="NaN" flip="True" mirrorvertically="False" mirrorhorizontally="False" hide="False" attackpriority="1" steerforce="0" density="10" ignorecollisions="False" angulardamping="7" pullpos="0,0" stepoffset="0,0" refjoint="-1" mouthpos="0,0" notes="" constanttorque="0" constantangle="0" scale="1" attackforcemultiplier="1" minseverancedamage="1" healthindex="0" friction="0.3" restitution="0.05" severedfadeouttime="10" applytailangle="False" sinefrequencymultiplier="1" sineamplitudemultiplier="1" blinkfrequency="0" blinkdurationin="0.2" blinkdurationout="0.5" blinkholdtime="0" blinkrotationin="0" blinkrotationout="45" blinkforce="50" blinktransitionin="Linear" blinktransitionout="Linear" inheritlimbdepth="None" onlyblinkinwater="False">
    <deformablesprite texture="" sourcerect="834,278,237,406" origin="0.5,0.5" depth="0.05" color="255,255,255,255" deadcolor="255,255,255,255" deadcolortime="0" subdivisions="5,5" ignoretint="False"></deformablesprite>
    <damagemodifier damagesound="" damagemultiplier="0.3" probabilitymultiplier="1" armorsector="0,360" deflectprojectiles="False" afflictionidentifiers="" afflictiontypes="damage" damageparticle="" />
    <damagemodifier damagesound="" damagemultiplier="0.1" probabilitymultiplier="1" armorsector="0,360" deflectprojectiles="False" afflictionidentifiers="" afflictiontypes="bleeding" damageparticle="" />
  </limb>
  <limb id="10" radius="70" width="175.1" height="562.7" name="Limb 10" type="None" spriteorientation="NaN" flip="True" mirrorvertically="False" mirrorhorizontally="False" hide="False" attackpriority="1" steerforce="0" density="10" ignorecollisions="False" angulardamping="7" pullpos="0,0" stepoffset="0,0" refjoint="-1" mouthpos="0,0" notes="" constanttorque="0" constantangle="0" scale="1" attackforcemultiplier="1" minseverancedamage="1" healthindex="0" friction="0.3" restitution="0.05" severedfadeouttime="10" applytailangle="False" sinefrequencymultiplier="1" sineamplitudemultiplier="1" blinkfrequency="0" blinkdurationin="0.2" blinkdurationout="0.5" blinkholdtime="0" blinkrotationin="0" blinkrotationout="45" blinkforce="50" blinktransitionin="Linear" blinktransitionout="Linear" inheritlimbdepth="None" onlyblinkinwater="False">
    <deformablesprite texture="" sourcerect="867,678,206,662" origin="0.5,0.5" depth="0.05" color="255,255,255,255" deadcolor="255,255,255,255" deadcolortime="0" subdivisions="5,5" ignoretint="False">
      <spritedeformation type="bendjoint" resolution="5,5" maxrotation="20" sync="-1" typename="bendjoint" blendmode="Add" strength="2" usemovementsine="False" stopwhenhostisdead="False" sineoffset="0" onlyinwater="False" />
    </deformablesprite>
    <damagemodifier damagesound="" damagemultiplier="0.3" probabilitymultiplier="1" armorsector="0,360" deflectprojectiles="False" afflictionidentifiers="" afflictiontypes="damage" damageparticle="" />
    <damagemodifier damagesound="" damagemultiplier="0.1" probabilitymultiplier="1" armorsector="0,360" deflectprojectiles="False" afflictionidentifiers="" afflictiontypes="bleeding" damageparticle="" />
  </limb>
  <limb id="11" radius="60" width="175.1" height="357" name="Limb 11" type="None" spriteorientation="NaN" flip="True" mirrorvertically="False" mirrorhorizontally="False" hide="False" attackpriority="1" steerforce="0" density="10" ignorecollisions="False" angulardamping="7" pullpos="0,0" stepoffset="0,0" refjoint="-1" mouthpos="0,0" notes="" constanttorque="0" constantangle="0" scale="1" attackforcemultiplier="1" minseverancedamage="1" healthindex="0" friction="0.3" restitution="0.05" severedfadeouttime="10" applytailangle="False" sinefrequencymultiplier="1" sineamplitudemultiplier="1" blinkfrequency="0" blinkdurationin="0.2" blinkdurationout="0.5" blinkholdtime="0" blinkrotationin="0" blinkrotationout="45" blinkforce="50" blinktransitionin="Linear" blinktransitionout="Linear" inheritlimbdepth="None" onlyblinkinwater="False">
    <deformablesprite texture="" sourcerect="866,1336,206,420" origin="0.5,0.5" depth="0.05" color="255,255,255,255" deadcolor="255,255,255,255" deadcolortime="0" subdivisions="5,5" ignoretint="False">
      <spritedeformation type="bendjoint" resolution="5,5" maxrotation="20" sync="-1" typename="bendjoint" blendmode="Add" strength="2" usemovementsine="False" stopwhenhostisdead="False" sineoffset="0" onlyinwater="False" />
    </deformablesprite>
    <damagemodifier damagesound="" damagemultiplier="0.3" probabilitymultiplier="1" armorsector="0,360" deflectprojectiles="False" afflictionidentifiers="" afflictiontypes="damage" damageparticle="" />
    <damagemodifier damagesound="" damagemultiplier="0.1" probabilitymultiplier="1" armorsector="0,360" deflectprojectiles="False" afflictionidentifiers="" afflictiontypes="bleeding" damageparticle="" />
  </limb>
  <limb id="12" radius="50" width="175.1" height="437.75" name="Limb 12" type="None" spriteorientation="NaN" flip="True" mirrorvertically="False" mirrorhorizontally="False" hide="False" attackpriority="1" steerforce="0" density="10" ignorecollisions="False" angulardamping="7" pullpos="0,0" stepoffset="0,0" refjoint="-1" mouthpos="0,0" notes="" constanttorque="0" constantangle="0" scale="1" attackforcemultiplier="1" minseverancedamage="1" healthindex="0" friction="0.3" restitution="0.05" severedfadeouttime="10" applytailangle="False" sinefrequencymultiplier="1" sineamplitudemultiplier="1" blinkfrequency="0" blinkdurationin="0.2" blinkdurationout="0.5" blinkholdtime="0" blinkrotationin="0" blinkrotationout="45" blinkforce="50" blinktransitionin="Linear" blinktransitionout="Linear" inheritlimbdepth="None" onlyblinkinwater="False">
    <deformablesprite texture="" sourcerect="867,1749,206,515" origin="0.5,0.5" depth="0.05" color="255,255,255,255" deadcolor="255,255,255,255" deadcolortime="0" subdivisions="5,5" ignoretint="False">
      <spritedeformation type="bendjoint" resolution="5,5" maxrotation="20" sync="-1" typename="bendjoint" blendmode="Add" strength="2" usemovementsine="False" stopwhenhostisdead="False" sineoffset="0" onlyinwater="False" />
    </deformablesprite>
    <damagemodifier damagesound="" damagemultiplier="0.3" probabilitymultiplier="1" armorsector="0,360" deflectprojectiles="False" afflictionidentifiers="" afflictiontypes="damage" damageparticle="" />
    <damagemodifier damagesound="" damagemultiplier="0.1" probabilitymultiplier="1" armorsector="0,360" deflectprojectiles="False" afflictionidentifiers="" afflictiontypes="bleeding" damageparticle="" />
  </limb>
  <limb id="13" width="228.65002" height="766.65" name="Limb 13" type="None" spriteorientation="NaN" flip="True" mirrorvertically="False" mirrorhorizontally="False" hide="False" attackpriority="1" steerforce="0" radius="110" density="10" ignorecollisions="False" angulardamping="7" pullpos="0,0" stepoffset="0,0" refjoint="-1" mouthpos="0,0" notes="" constanttorque="0" constantangle="0" scale="1" attackforcemultiplier="1" minseverancedamage="1" healthindex="0" friction="0.3" restitution="0.05" severedfadeouttime="10" applytailangle="False" sinefrequencymultiplier="1" sineamplitudemultiplier="1" blinkfrequency="0" blinkdurationin="0.2" blinkdurationout="0.5" blinkholdtime="0" blinkrotationin="0" blinkrotationout="45" blinkforce="50" blinktransitionin="Linear" blinktransitionout="Linear" inheritlimbdepth="None" onlyblinkinwater="False">
    <sprite texture="" sourcerect="165,1743,269,1149" origin="0.5,0.5" depth="0" color="255,255,255,255" deadcolor="255,255,255,255" deadcolortime="0" ignoretint="False" />
    <damagemodifier damagesound="" damagemultiplier="0" probabilitymultiplier="1" armorsector="0,360" deflectprojectiles="False" afflictionidentifiers="" afflictiontypes="bleeding" damageparticle="" />
    <damagemodifier damagesound="" damagemultiplier="0.3" probabilitymultiplier="1" armorsector="0,360" deflectprojectiles="False" afflictionidentifiers="" afflictiontypes="damage" damageparticle="" />
  </limb>
  <limb Name="Limb 14" ID="14" Type="None" Notes="" Scale="1" Flip="True" MirrorVertically="False" MirrorHorizontally="False" Hide="False" SpriteOrientation="NaN" InheritLimbDepth="None" SteerForce="0" Radius="0" Height="294" Width="165" Density="10" IgnoreCollisions="False" AngularDamping="7" AttackPriority="1" PullPos="0,0" StepOffset="0,0" RefJoint="-1" MouthPos="0,0" ConstantTorque="0" ConstantAngle="0" AttackForceMultiplier="1" MinSeveranceDamage="1" CanBeSeveredAlive="True" SeveredFadeOutTime="10" ApplyTailAngle="False" SineFrequencyMultiplier="1" SineAmplitudeMultiplier="1" BlinkFrequency="0" BlinkDurationIn="0.2" BlinkDurationOut="0.5" BlinkHoldTime="0" BlinkRotationIn="0" BlinkRotationOut="45" BlinkForce="50" OnlyBlinkInWater="False" BlinkTransitionIn="Linear" BlinkTransitionOut="Linear" HealthIndex="0" Friction="0.3" Restitution="0.05">
    <sprite SourceRect="1181,375,165,294" Origin="0.5,0.5" Depth="0" Texture="" IgnoreTint="False" Color="255,255,255,255" DeadColor="255,255,255,255" DeadColorTime="0" />
  </limb>
  <limb Name="Limb 15" ID="15" Type="None" Notes="" Scale="1" Flip="True" MirrorVertically="False" MirrorHorizontally="False" Hide="False" SpriteOrientation="NaN" InheritLimbDepth="None" SteerForce="0" Radius="0" Height="294" Width="165" Density="10" IgnoreCollisions="False" AngularDamping="7" AttackPriority="1" PullPos="0,0" StepOffset="0,0" RefJoint="-1" MouthPos="0,0" ConstantTorque="0" ConstantAngle="0" AttackForceMultiplier="1" MinSeveranceDamage="1" CanBeSeveredAlive="True" SeveredFadeOutTime="10" ApplyTailAngle="False" SineFrequencyMultiplier="1" SineAmplitudeMultiplier="1" BlinkFrequency="0" BlinkDurationIn="0.2" BlinkDurationOut="0.5" BlinkHoldTime="0" BlinkRotationIn="0" BlinkRotationOut="45" BlinkForce="50" OnlyBlinkInWater="False" BlinkTransitionIn="Linear" BlinkTransitionOut="Linear" HealthIndex="0" Friction="0.3" Restitution="0.05">
    <sprite SourceRect="1181,375,165,294" Origin="0.5,0.5" Depth="0" Texture="" IgnoreTint="False" Color="255,255,255,255" DeadColor="255,255,255,255" DeadColorTime="0" />
  </limb>
  <limb Name="Limb 16" ID="16" Type="None" Notes="" Scale="1" Flip="True" MirrorVertically="False" MirrorHorizontally="False" Hide="False" SpriteOrientation="NaN" InheritLimbDepth="None" SteerForce="0" Radius="0" Height="570" Width="239" Density="10" IgnoreCollisions="False" AngularDamping="7" AttackPriority="1" PullPos="0,0" StepOffset="0,0" RefJoint="-1" MouthPos="0,0" ConstantTorque="0" ConstantAngle="0" AttackForceMultiplier="1" MinSeveranceDamage="1" CanBeSeveredAlive="True" SeveredFadeOutTime="10" ApplyTailAngle="False" SineFrequencyMultiplier="1" SineAmplitudeMultiplier="1" BlinkFrequency="0" BlinkDurationIn="0.2" BlinkDurationOut="0.5" BlinkHoldTime="0" BlinkRotationIn="0" BlinkRotationOut="45" BlinkForce="50" OnlyBlinkInWater="False" BlinkTransitionIn="Linear" BlinkTransitionOut="Linear" HealthIndex="0" Friction="0.3" Restitution="0.05">
    <sprite SourceRect="1126,743,239,570" Origin="0.5,0.5" Depth="0" Texture="" IgnoreTint="False" Color="255,255,255,255" DeadColor="255,255,255,255" DeadColorTime="0" />
  </limb>
  <limb Name="Limb 17" ID="17" Type="None" Notes="" Scale="1" Flip="True" MirrorVertically="False" MirrorHorizontally="False" Hide="False" SpriteOrientation="NaN" InheritLimbDepth="None" SteerForce="0" Radius="0" Height="570" Width="239" Density="10" IgnoreCollisions="False" AngularDamping="7" AttackPriority="1" PullPos="0,0" StepOffset="0,0" RefJoint="-1" MouthPos="0,0" ConstantTorque="0" ConstantAngle="0" AttackForceMultiplier="1" MinSeveranceDamage="1" CanBeSeveredAlive="True" SeveredFadeOutTime="10" ApplyTailAngle="False" SineFrequencyMultiplier="1" SineAmplitudeMultiplier="1" BlinkFrequency="0" BlinkDurationIn="0.2" BlinkDurationOut="0.5" BlinkHoldTime="0" BlinkRotationIn="0" BlinkRotationOut="45" BlinkForce="50" OnlyBlinkInWater="False" BlinkTransitionIn="Linear" BlinkTransitionOut="Linear" HealthIndex="0" Friction="0.3" Restitution="0.05">
    <sprite SourceRect="1126,743,239,570" Origin="0.5,0.5" Depth="0" Texture="" IgnoreTint="False" Color="255,255,255,255" DeadColor="255,255,255,255" DeadColorTime="0" />
  </limb>
  <limb Name="Limb 18" ID="18" Type="None" Notes="" Scale="1" Flip="True" MirrorVertically="False" MirrorHorizontally="False" Hide="False" SpriteOrientation="NaN" InheritLimbDepth="None" SteerForce="0" Radius="0" Height="570" Width="239" Density="10" IgnoreCollisions="False" AngularDamping="7" AttackPriority="1" PullPos="0,0" StepOffset="0,0" RefJoint="-1" MouthPos="0,0" ConstantTorque="0" ConstantAngle="0" AttackForceMultiplier="1" MinSeveranceDamage="1" CanBeSeveredAlive="True" SeveredFadeOutTime="10" ApplyTailAngle="False" SineFrequencyMultiplier="1" SineAmplitudeMultiplier="1" BlinkFrequency="0" BlinkDurationIn="0.2" BlinkDurationOut="0.5" BlinkHoldTime="0" BlinkRotationIn="0" BlinkRotationOut="45" BlinkForce="50" OnlyBlinkInWater="False" BlinkTransitionIn="Linear" BlinkTransitionOut="Linear" HealthIndex="0" Friction="0.3" Restitution="0.05">
    <sprite SourceRect="1126,743,239,570" Origin="0.5,0.5" Depth="0" Texture="" IgnoreTint="False" Color="255,255,255,255" DeadColor="255,255,255,255" DeadColorTime="0" />
  </limb>
  <joint Name="Joint 0 - 1" Limb1="0" Limb2="1" Limb1Anchor="7.6395526,417.38968" Limb2Anchor="7.6490088,-248.10109" CanBeSevered="True" SeveranceProbabilityModifier="0" BreakSound="gore" LimitEnabled="True" UpperLimit="22" LowerLimit="-22" Stiffness="0.25" Scale="1" WeldJoint="False" ClockWiseRotation="False" />
  <joint Name="Joint 0 - 2" Limb1="0" Limb2="2" Limb1Anchor="-21.165966,-420.25467" Limb2Anchor="3.6302667,408.62494" CanBeSevered="True" SeveranceProbabilityModifier="0" BreakSound="gore" LimitEnabled="True" UpperLimit="22" LowerLimit="-22" Stiffness="0.25" Scale="1" WeldJoint="False" ClockWiseRotation="False" />
  <joint Name="Joint 2 - 3" Limb1="2" Limb2="3" Limb1Anchor="-7.080862,-408.25833" Limb2Anchor="-3.4313176,309.04724" CanBeSevered="True" SeveranceProbabilityModifier="0" BreakSound="gore" LimitEnabled="True" UpperLimit="22" LowerLimit="-22" Stiffness="0.25" Scale="1" WeldJoint="False" ClockWiseRotation="False" />
  <joint Name="Joint 3 - 4" Limb1="3" Limb2="4" Limb1Anchor="-29.54573,-309.105" Limb2Anchor="-30.693048,360.9242" CanBeSevered="True" SeveranceProbabilityModifier="0" BreakSound="gore" LimitEnabled="True" UpperLimit="22" LowerLimit="-22" Stiffness="0.25" Scale="1" WeldJoint="False" ClockWiseRotation="False" />
  <joint Name="Joint 0 - 5" Limb1="0" Limb2="5" Limb1Anchor="-188.86497,62.162228" Limb2Anchor="28.294659,118.01241" CanBeSevered="True" SeveranceProbabilityModifier="0.1" BreakSound="gore" LimitEnabled="True" UpperLimit="15" LowerLimit="-15" Stiffness="0.25" Scale="1" WeldJoint="False" ClockWiseRotation="False" />
  <joint Name="Joint 5 - 6" Limb1="5" Limb2="6" Limb1Anchor="-22.09,-165.69" Limb2Anchor="-3.68,335.05" CanBeSevered="True" SeveranceProbabilityModifier="0.1" BreakSound="gore" LimitEnabled="True" UpperLimit="15" LowerLimit="-15" Stiffness="0.25" Scale="1" WeldJoint="False" ClockWiseRotation="False" />
  <joint Name="Joint 6 - 7" Limb1="6" Limb2="7" Limb1Anchor="-18.41,-316.64" Limb2Anchor="-18.41,220.91" CanBeSevered="True" SeveranceProbabilityModifier="0.15" BreakSound="gore" LimitEnabled="True" UpperLimit="15" LowerLimit="-15" Stiffness="0.25" Scale="1" WeldJoint="False" ClockWiseRotation="False" />
  <joint Name="Joint 7 - 8" Limb1="7" Limb2="8" Limb1Anchor="-0,-198.82" Limb2Anchor="-0,261.42" CanBeSevered="True" SeveranceProbabilityModifier="0.2" BreakSound="gore" LimitEnabled="True" UpperLimit="15" LowerLimit="-15" Stiffness="0.25" Scale="1" WeldJoint="False" ClockWiseRotation="False" />
  <joint Name="Joint 2 - 8" Limb1="2" Limb2="13" Limb1Anchor="-51.253426,-25.202" Limb2Anchor="89.231155,496.54593" CanBeSevered="True" SeveranceProbabilityModifier="0.1" BreakSound="gore" LimitEnabled="True" UpperLimit="59" LowerLimit="-27.000011" Stiffness="0.25" Scale="1" WeldJoint="False" ClockWiseRotation="False" />
  <joint Name="Joint 1 - 9" Limb1="1" Limb2="9" Limb1Anchor="145.82162,-74.161354" Limb2Anchor="-55.23,117.82" CanBeSevered="True" SeveranceProbabilityModifier="0.1" BreakSound="gore" LimitEnabled="True" UpperLimit="21" LowerLimit="0" Stiffness="0.25" Scale="1" WeldJoint="False" ClockWiseRotation="False" />
  <joint Name="Joint 9 - 10" Limb1="9" Limb2="10" Limb1Anchor="18.333607,-192.0516" Limb2Anchor="-0,338.74" CanBeSevered="True" SeveranceProbabilityModifier="0.1" BreakSound="gore" LimitEnabled="True" UpperLimit="15" LowerLimit="-15" Stiffness="0.25" Scale="1" WeldJoint="False" ClockWiseRotation="False" />
  <joint Name="Joint 10 - 11" Limb1="10" Limb2="11" Limb1Anchor="14.73,-316.67868" Limb2Anchor="14.73,217.23" CanBeSevered="True" SeveranceProbabilityModifier="0.15" BreakSound="gore" LimitEnabled="True" UpperLimit="15" LowerLimit="-15" Stiffness="0.25" Scale="1" WeldJoint="False" ClockWiseRotation="False" />
  <joint Name="Joint 11 - 12" Limb1="11" Limb2="12" Limb1Anchor="-3.68,-198.82" Limb2Anchor="-3.68,261.42" CanBeSevered="True" SeveranceProbabilityModifier="0.2" BreakSound="gore" LimitEnabled="True" UpperLimit="15" LowerLimit="-15" Stiffness="0.25" Scale="1" WeldJoint="False" ClockWiseRotation="False" />
  <joint Name="Joint 14 - 1" Limb1="14" Limb2="1" Limb1Anchor="7.36,62.59" Limb2Anchor="-99.41,0" CanBeSevered="True" SeveranceProbabilityModifier="0" BreakSound="gore" LimitEnabled="True" UpperLimit="0" LowerLimit="0" Stiffness="0.25" Scale="1" WeldJoint="False" ClockWiseRotation="False" />
  <joint Name="Joint 15 - 1" Limb1="15" Limb2="1" Limb1Anchor="91.54,662.44" Limb2Anchor="110.46,-58.91" CanBeSevered="True" SeveranceProbabilityModifier="0" BreakSound="gore" LimitEnabled="True" UpperLimit="0" LowerLimit="0" Stiffness="0.25" Scale="1" WeldJoint="False" ClockWiseRotation="False" />
  <joint Name="Joint 16 - 0" Limb1="16" Limb2="0" Limb1Anchor="-102.98611,92.793564" Limb2Anchor="-143.59,136.23" CanBeSevered="True" SeveranceProbabilityModifier="0" BreakSound="gore" LimitEnabled="True" UpperLimit="0" LowerLimit="0" Stiffness="0.25" Scale="1" WeldJoint="False" ClockWiseRotation="False" />
  <joint Name="Joint 17 - 0" Limb1="17" Limb2="0" Limb1Anchor="0.22298396,68.408745" Limb2Anchor="154.64,143.59" CanBeSevered="True" SeveranceProbabilityModifier="0" BreakSound="gore" LimitEnabled="True" UpperLimit="0" LowerLimit="0" Stiffness="0.25" Scale="1" WeldJoint="False" ClockWiseRotation="False" />
  <joint Name="Joint 18 - 0" Limb1="18" Limb2="0" Limb1Anchor="-65.52353,225.74442" Limb2Anchor="-3.68,-243.01" CanBeSevered="True" SeveranceProbabilityModifier="0" BreakSound="gore" LimitEnabled="True" UpperLimit="0" LowerLimit="0" Stiffness="0.25" Scale="1" WeldJoint="False" ClockWiseRotation="False" />
</Ragdoll>