<?xml version="1.0" encoding="utf-8"?>
<Ragdoll type="Shadowwhale" texture="%ModDir%/Characters/ExtendedMonsterCreatures/Shadowwhale/ShadowWhale.png" canentersubmarine="False" canwalk="False" spritesheetorientation="0" limbscale="1.6637" jointscale="1.6637" texturescale="1" colliderheightfromfloor="45" impacttolerance="50" draggable="True" mainlimb="Torso" color="255,255,255,255">
  <collider radius="122" width="1" name="Main Collider" height="310" />
  <limb id="0" name="Limb 0" type="Torso" height="0" width="117" notes="" spriteorientation="NaN" flip="True" mirrorvertically="False" mirrorhorizontally="False" hide="False" attackpriority="1" steerforce="0" radius="50.3" density="10" ignorecollisions="False" angulardamping="7" pullpos="0,0" stepoffset="0,0" refjoint="-1" mouthpos="0,0" constanttorque="0" constantangle="0" scale="1" attackforcemultiplier="1" minseverancedamage="1" healthindex="0" friction="0.3" restitution="0.05" severedfadeouttime="10" applytailangle="False" sinefrequencymultiplier="1" sineamplitudemultiplier="1" blinkfrequency="0" blinkdurationin="0.2" blinkdurationout="0.5" blinkholdtime="0" blinkrotationin="0" blinkrotationout="45" blinkforce="50" blinktransitionin="Linear" blinktransitionout="Linear" inheritlimbdepth="None" onlyblinkinwater="False">
    <deformablesprite texture="" sourcerect="963,248,183,163" origin="0.5,0.5" depth="0" color="255,255,255,255" deadcolor="255,255,255,255" deadcolortime="0" subdivisions="3,3" ignoretint="False">
      <spritedeformation type="bendjoint" resolution="3,3" sync="-1" typename="bendjoint" blendmode="Add" usemovementsine="False" stopwhenhostisdead="False" sineoffset="0" maxrotation="20" strength="2" onlyinwater="False" />
    </deformablesprite>
  </limb>
  <limb id="1" name="Limb 1" type="Head" height="0" width="116.45" notes="" spriteorientation="NaN" flip="True" mirrorvertically="False" mirrorhorizontally="False" hide="False" attackpriority="1" steerforce="10" radius="58.850006" density="30" ignorecollisions="False" angulardamping="7" pullpos="0,0" stepoffset="0,0" refjoint="-1" mouthpos="0,0" constanttorque="0" constantangle="0" scale="1" attackforcemultiplier="1" minseverancedamage="1" healthindex="0" friction="0.3" restitution="0.05" severedfadeouttime="10" applytailangle="False" sinefrequencymultiplier="1" sineamplitudemultiplier="1" blinkfrequency="0" blinkdurationin="0.2" blinkdurationout="0.5" blinkholdtime="0" blinkrotationin="0" blinkrotationout="45" blinkforce="50" blinktransitionin="Linear" blinktransitionout="Linear" inheritlimbdepth="None" onlyblinkinwater="False">
    <deformablesprite texture="" sourcerect="1143,249,299,162" origin="0.5,0.5" depth="0" color="255,255,255,255" deadcolor="255,255,255,255" deadcolortime="0" subdivisions="3,3" ignoretint="False">
      <spritedeformation type="bendjoint" resolution="3,3" sync="-1" typename="bendjoint" blendmode="Add" usemovementsine="False" stopwhenhostisdead="False" sineoffset="0" maxrotation="20" strength="2.5" onlyinwater="False" />
    </deformablesprite>
    <attack structuresoundtype="StructureBlunt" context="Any" targettype="Any" targetlimbtype="None" hitdetectiontype="Distance" afterattack="FallBackUntilCanAttack" afterattackdelay="0" reverse="False" retreat="False" range="300" damagerange="320" duration="0.25" cooldown="10" secondarycooldown="0" cooldownrandomfactor="0" structuredamage="60" itemdamage="30" stun="0" onlyhumans="False" applyforceonlimbs="" force="7" rootforceworldstart="0,0" rootforceworldmiddle="0,0" rootforceworldend="0,0" roottransitioneasing="Linear" torque="0" applyforcesonlyonce="False" targetimpulse="500" targetimpulseworld="0,0" targetforce="0" targetforceworld="0,0" severlimbsprobability="0" priority="0" fullspeedafterattack="False" penetration="0" levelwalldamage="60" ranged="False" avoidfriendlyfire="False" requiredangle="20" submarineimpactmultiplier="1" blink="False">
      <affliction identifier="blunttrauma" strength="50" probability="1" />
      <affliction identifier="stun" strength="10" probability="1" />
    </attack>
    <lightsource color="255,82,0,93" range="260" scale="1" offset="0,0" rotation="0" flicker="0" flickerspeed="1" pulsefrequency="0" pulseamount="0" blinkfrequency="0">
      <lighttexture texture="Content/Lights/pointlight_bright.png" origin="0.46,0.55" size="1,1" />
    </lightsource>
  </limb>
  <limb id="2" width="103.59999" height="0" name="Limb 2" type="None" spriteorientation="NaN" flip="True" mirrorvertically="False" mirrorhorizontally="False" hide="False" attackpriority="1" steerforce="0" radius="40.9" density="10" ignorecollisions="False" angulardamping="7" pullpos="0,0" stepoffset="0,0" refjoint="-1" mouthpos="0,0" notes="" constanttorque="0" constantangle="0" scale="1" attackforcemultiplier="1" minseverancedamage="1" healthindex="0" friction="0.3" restitution="0.05" severedfadeouttime="10" applytailangle="False" sinefrequencymultiplier="1" sineamplitudemultiplier="1" blinkfrequency="0" blinkdurationin="0.2" blinkdurationout="0.5" blinkholdtime="0" blinkrotationin="0" blinkrotationout="45" blinkforce="50" blinktransitionin="Linear" blinktransitionout="Linear" inheritlimbdepth="None" onlyblinkinwater="False">
    <deformablesprite texture="" sourcerect="788,249,178,162" origin="0.5,0.5" depth="0" color="255,255,255,255" deadcolor="255,255,255,255" deadcolortime="0" subdivisions="3,3" ignoretint="False">
      <spritedeformation type="bendjoint" resolution="3,3" sync="-1" typename="bendjoint" blendmode="Add" usemovementsine="False" stopwhenhostisdead="False" sineoffset="0" maxrotation="20" strength="2" onlyinwater="False" />
    </deformablesprite>
  </limb>
  <limb id="3" radius="30" width="117" height="0" name="Limb 3" type="None" spriteorientation="NaN" flip="True" mirrorvertically="False" mirrorhorizontally="False" hide="False" attackpriority="1" steerforce="0" density="10" ignorecollisions="False" angulardamping="7" pullpos="0,0" stepoffset="0,0" refjoint="-1" mouthpos="0,0" notes="" constanttorque="0" constantangle="0" scale="1" attackforcemultiplier="1" minseverancedamage="1" healthindex="0" friction="0.3" restitution="0.05" severedfadeouttime="10" applytailangle="False" sinefrequencymultiplier="1" sineamplitudemultiplier="1" blinkfrequency="0" blinkdurationin="0.2" blinkdurationout="0.5" blinkholdtime="0" blinkrotationin="0" blinkrotationout="45" blinkforce="50" blinktransitionin="Linear" blinktransitionout="Linear" inheritlimbdepth="None" onlyblinkinwater="False">
    <deformablesprite texture="" sourcerect="608,247,184,164" origin="0.52798647,0.45383278" depth="0" color="255,255,255,255" deadcolor="255,255,255,255" deadcolortime="0" subdivisions="3,3" ignoretint="False">
      <spritedeformation type="bendjoint" resolution="3,3" sync="-1" typename="bendjoint" blendmode="Add" usemovementsine="False" stopwhenhostisdead="False" sineoffset="0" maxrotation="20" strength="2" onlyinwater="False" />
    </deformablesprite>
  </limb>
  <limb id="4" radius="20" width="132.95" height="0" name="Limb 4" type="None" spriteorientation="NaN" flip="True" mirrorvertically="False" mirrorhorizontally="False" hide="False" attackpriority="1" steerforce="0" density="10" ignorecollisions="False" angulardamping="7" pullpos="0,0" stepoffset="0,0" refjoint="-1" mouthpos="0,0" notes="" constanttorque="0" constantangle="0" scale="1" attackforcemultiplier="1" minseverancedamage="1" healthindex="0" friction="0.3" restitution="0.05" severedfadeouttime="10" applytailangle="False" sinefrequencymultiplier="1" sineamplitudemultiplier="1" blinkfrequency="0" blinkdurationin="0.2" blinkdurationout="0.5" blinkholdtime="0" blinkrotationin="0" blinkrotationout="45" blinkforce="50" blinktransitionin="Linear" blinktransitionout="Linear" inheritlimbdepth="None" onlyblinkinwater="False">
    <deformablesprite texture="" sourcerect="426,249,189,162" origin="0.47503033,0.41632834" depth="0" color="255,255,255,255" deadcolor="255,255,255,255" deadcolortime="0" subdivisions="3,3" ignoretint="False">
      <spritedeformation type="bendjoint" resolution="3,3" sync="-1" typename="bendjoint" blendmode="Add" usemovementsine="False" stopwhenhostisdead="False" sineoffset="0" maxrotation="20" strength="2" onlyinwater="False" />
    </deformablesprite>
  </limb>
  <limb id="5" radius="18" width="100" height="0" name="Limb 5" type="Tail" spriteorientation="NaN" flip="True" mirrorvertically="False" mirrorhorizontally="False" hide="False" attackpriority="1" steerforce="0" density="10" ignorecollisions="False" angulardamping="7" pullpos="0,0" stepoffset="0,0" refjoint="-1" mouthpos="0,0" notes="" constanttorque="0" constantangle="0" scale="1" attackforcemultiplier="1" minseverancedamage="1" healthindex="0" friction="0.3" restitution="0.05" severedfadeouttime="10" applytailangle="False" sinefrequencymultiplier="1" sineamplitudemultiplier="1" blinkfrequency="0" blinkdurationin="0.2" blinkdurationout="0.5" blinkholdtime="0" blinkrotationin="0" blinkrotationout="45" blinkforce="50" blinktransitionin="Linear" blinktransitionout="Linear" inheritlimbdepth="None" onlyblinkinwater="False">
    <deformablesprite texture="" sourcerect="307,248,120,163" origin="0.49399224,0.37404966" depth="0" color="255,255,255,255" deadcolor="255,255,255,255" deadcolortime="0" subdivisions="3,3" ignoretint="False">
      <spritedeformation type="bendjoint" resolution="3,3" sync="-1" typename="bendjoint" blendmode="Add" usemovementsine="False" stopwhenhostisdead="False" sineoffset="0" maxrotation="20" strength="2" onlyinwater="False" />
    </deformablesprite>
  </limb>
  <limb id="6" radius="14" width="100" height="0" name="Limb 6" type="None" spriteorientation="NaN" flip="True" mirrorvertically="False" mirrorhorizontally="False" hide="False" attackpriority="1" steerforce="0" density="10" ignorecollisions="False" angulardamping="7" pullpos="0,0" stepoffset="0,0" refjoint="-1" mouthpos="0,0" notes="" constanttorque="0" constantangle="0" scale="1" attackforcemultiplier="1" minseverancedamage="1" healthindex="0" friction="0.3" restitution="0.05" severedfadeouttime="10" applytailangle="False" sinefrequencymultiplier="1" sineamplitudemultiplier="1" blinkfrequency="0" blinkdurationin="0.2" blinkdurationout="0.5" blinkholdtime="0" blinkrotationin="0" blinkrotationout="45" blinkforce="50" blinktransitionin="Linear" blinktransitionout="Linear" inheritlimbdepth="None" onlyblinkinwater="False">
    <deformablesprite texture="" sourcerect="181,247,130,162" origin="0.46687964,0.41329315" depth="0" color="255,255,255,255" deadcolor="255,255,255,255" deadcolortime="0" subdivisions="3,3" ignoretint="False">
      <spritedeformation type="bendjoint" resolution="3,3" sync="-1" typename="bendjoint" blendmode="Add" usemovementsine="False" stopwhenhostisdead="False" sineoffset="0" maxrotation="20" strength="2" onlyinwater="False" />
    </deformablesprite>
  </limb>
  <limb id="7" width="0" height="0" name="Limb 7" type="None" spriteorientation="NaN" flip="True" mirrorvertically="False" mirrorhorizontally="False" hide="False" attackpriority="1" steerforce="0" radius="83.125" density="17" ignorecollisions="False" angulardamping="7" pullpos="0,0" stepoffset="0,0" refjoint="-1" mouthpos="0,0" notes="" constanttorque="0" constantangle="0" scale="1" attackforcemultiplier="1" minseverancedamage="1" healthindex="0" friction="0.3" restitution="0.05" severedfadeouttime="10" applytailangle="False" sinefrequencymultiplier="1" sineamplitudemultiplier="1" blinkfrequency="0" blinkdurationin="0.2" blinkdurationout="0.5" blinkholdtime="0" blinkrotationin="0" blinkrotationout="45" blinkforce="50" blinktransitionin="Linear" blinktransitionout="Linear" inheritlimbdepth="None" onlyblinkinwater="False">
    <deformablesprite texture="" sourcerect="1166,94,251,125" origin="0.40746003,0.7629502" depth="0" color="255,255,255,255" deadcolor="255,255,255,255" deadcolortime="0" subdivisions="3,3" ignoretint="False">
      <spritedeformation type="bendjoint" resolution="3,3" sync="-1" typename="bendjoint" blendmode="Add" usemovementsine="False" stopwhenhostisdead="False" sineoffset="0" maxrotation="20" strength="0" onlyinwater="False" />
    </deformablesprite>
    <damagemodifier damagesound="" damagemultiplier="0.2" probabilitymultiplier="1" armorsector="0,360" deflectprojectiles="False" afflictionidentifiers="" afflictiontypes="damage" damageparticle="" />
  </limb>
  <limb id="8" radius="75.25" width="0" height="0" name="Limb 8" type="None" spriteorientation="NaN" flip="True" mirrorvertically="False" mirrorhorizontally="False" hide="False" attackpriority="1" steerforce="0" density="17" ignorecollisions="False" angulardamping="7" pullpos="0,0" stepoffset="0,0" refjoint="-1" mouthpos="0,0" notes="" constanttorque="0" constantangle="0" scale="1" attackforcemultiplier="1" minseverancedamage="1" healthindex="0" friction="0.3" restitution="0.05" severedfadeouttime="10" applytailangle="False" sinefrequencymultiplier="1" sineamplitudemultiplier="1" blinkfrequency="0" blinkdurationin="0.2" blinkdurationout="0.5" blinkholdtime="0" blinkrotationin="0" blinkrotationout="45" blinkforce="50" blinktransitionin="Linear" blinktransitionout="Linear" inheritlimbdepth="None" onlyblinkinwater="False">
    <deformablesprite texture="" sourcerect="1166,448,214,130" origin="0.39640468,0.27222082" depth="0" color="255,255,255,255" deadcolor="255,255,255,255" deadcolortime="0" subdivisions="3,3" ignoretint="False">
      <spritedeformation type="bendjoint" resolution="3,3" sync="-1" typename="bendjoint" blendmode="Add" usemovementsine="False" stopwhenhostisdead="False" sineoffset="0" maxrotation="20" strength="0.5" onlyinwater="False" />
    </deformablesprite>
    <damagemodifier damagesound="" damagemultiplier="0.2" probabilitymultiplier="1" armorsector="0,360" deflectprojectiles="False" afflictionidentifiers="" afflictiontypes="damage" damageparticle="" />
  </limb>
  <limb id="9" width="300.84998" height="0" name="Limb 9" type="None" spriteorientation="NaN" flip="True" mirrorvertically="False" mirrorhorizontally="False" hide="False" attackpriority="1" steerforce="0" radius="16.975002" density="10" ignorecollisions="False" angulardamping="7" pullpos="0,0" stepoffset="0,0" refjoint="-1" mouthpos="0,0" notes="" constanttorque="0" constantangle="0" scale="1" attackforcemultiplier="1" minseverancedamage="1" healthindex="0" friction="0.3" restitution="0.05" severedfadeouttime="10" applytailangle="False" sinefrequencymultiplier="1" sineamplitudemultiplier="1" blinkfrequency="0" blinkdurationin="0.2" blinkdurationout="0.5" blinkholdtime="0" blinkrotationin="0" blinkrotationout="45" blinkforce="50" blinktransitionin="Linear" blinktransitionout="Linear" inheritlimbdepth="None" onlyblinkinwater="False">
    <deformablesprite texture="" sourcerect="880,508,288,87" origin="0.51760334,0.490396" depth="0" color="255,255,255,255" deadcolor="255,255,255,255" deadcolortime="0" subdivisions="3,3" ignoretint="False">
      <spritedeformation type="bendjoint" resolution="3,3" sync="-1" typename="bendjoint" blendmode="Add" usemovementsine="False" stopwhenhostisdead="False" sineoffset="0" maxrotation="20" strength="2" onlyinwater="False" />
    </deformablesprite>
    <damagemodifier damagesound="" damagemultiplier="0.2" probabilitymultiplier="1" armorsector="0,360" deflectprojectiles="False" afflictionidentifiers="" afflictiontypes="damage" damageparticle="" />
  </limb>
  <limb id="10" width="215.35" height="0" name="Limb 10" type="None" spriteorientation="NaN" flip="True" mirrorvertically="False" mirrorhorizontally="False" hide="False" attackpriority="1" steerforce="0" radius="16.975002" density="10" ignorecollisions="False" angulardamping="7" pullpos="0,0" stepoffset="0,0" refjoint="-1" mouthpos="0,0" notes="" constanttorque="0" constantangle="0" scale="1" attackforcemultiplier="1" minseverancedamage="1" healthindex="0" friction="0.3" restitution="0.05" severedfadeouttime="10" applytailangle="False" sinefrequencymultiplier="1" sineamplitudemultiplier="1" blinkfrequency="0" blinkdurationin="0.2" blinkdurationout="0.5" blinkholdtime="0" blinkrotationin="0" blinkrotationout="45" blinkforce="50" blinktransitionin="Linear" blinktransitionout="Linear" inheritlimbdepth="None" onlyblinkinwater="False">
    <deformablesprite texture="" sourcerect="626,508,258,87" origin="0.5192511,0.40447545" depth="0" color="255,255,255,255" deadcolor="255,255,255,255" deadcolortime="0" subdivisions="3,3" ignoretint="False">
      <spritedeformation type="bendjoint" resolution="3,3" sync="-1" typename="bendjoint" blendmode="Add" usemovementsine="False" stopwhenhostisdead="False" sineoffset="0" maxrotation="20" strength="2" onlyinwater="False" />
    </deformablesprite>
    <attack duration="0.15" structuredamage="5" structuresoundtype="StructureSlash" torque="1000" force="10" targetimpulse="20" severlimbsprobability="0" context="Any" targettype="Character" hitdetectiontype="Distance" afterattack="FallBack" cooldown="10" secondarycooldown="0" itemdamage="5" stun="0" onlyhumans="False" applyforceonlimbs="" applyforcesonlyonce="False" targetimpulseworld="0,0" targetforceworld="0,0" stickchance="0" priority="0.25" cooldownrandomfactor="0" targetforce="0" range="100" damagerange="150" reverse="False" retreat="False" targetlimbtype="None" targetdistance="0" afterattackdelay="0" rootforceworldstart="0,0" rootforceworldmiddle="0,0" rootforceworldend="0,0" roottransitioneasing="Linear" fullspeedafterattack="False" penetration="0" levelwalldamage="5" ranged="False" avoidfriendlyfire="False" requiredangle="20" submarineimpactmultiplier="1" blink="False">
      <Affliction identifier="bitewounds" strength="10" probability="1" />
      <Affliction identifier="stun" strength="1" probability="1" />
    </attack>
    <damagemodifier damagesound="" damagemultiplier="0.1" probabilitymultiplier="1" armorsector="0,360" deflectprojectiles="False" afflictionidentifiers="" afflictiontypes="damage" damageparticle="" />
  </limb>
  <limb id="11" radius="15.925001" width="287.25" height="0" name="Limb 11" type="None" spriteorientation="NaN" flip="True" mirrorvertically="False" mirrorhorizontally="False" hide="False" attackpriority="1" steerforce="0" density="10" ignorecollisions="False" angulardamping="7" pullpos="0,0" stepoffset="0,0" refjoint="-1" mouthpos="0,0" notes="" constanttorque="0" constantangle="0" scale="1" attackforcemultiplier="1" minseverancedamage="1" healthindex="0" friction="0.3" restitution="0.05" severedfadeouttime="10" applytailangle="False" sinefrequencymultiplier="1" sineamplitudemultiplier="1" blinkfrequency="0" blinkdurationin="0.2" blinkdurationout="0.5" blinkholdtime="0" blinkrotationin="0" blinkrotationout="45" blinkforce="50" blinktransitionin="Linear" blinktransitionout="Linear" inheritlimbdepth="None" onlyblinkinwater="False">
    <deformablesprite texture="" sourcerect="922,98,246,61" origin="0.5567891,0.39496765" depth="0" color="255,255,255,255" deadcolor="255,255,255,255" deadcolortime="0" subdivisions="3,3" ignoretint="False">
      <spritedeformation type="bendjoint" resolution="3,3" sync="-1" typename="bendjoint" blendmode="Add" usemovementsine="False" stopwhenhostisdead="False" sineoffset="0" maxrotation="20" strength="1" onlyinwater="False" />
    </deformablesprite>
    <damagemodifier damagesound="" damagemultiplier="0.2" probabilitymultiplier="1" armorsector="0,360" deflectprojectiles="False" afflictionidentifiers="" afflictiontypes="damage" damageparticle="" />
  </limb>
  <limb id="12" radius="16.9" width="140.75" height="0" name="Limb 12" type="None" spriteorientation="NaN" flip="True" mirrorvertically="False" mirrorhorizontally="False" hide="False" attackpriority="1" steerforce="0" density="10" ignorecollisions="False" angulardamping="7" pullpos="0,0" stepoffset="0,0" refjoint="-1" mouthpos="0,0" notes="" constanttorque="0" constantangle="0" scale="1" attackforcemultiplier="1" minseverancedamage="1" healthindex="0" friction="0.3" restitution="0.05" severedfadeouttime="10" applytailangle="False" sinefrequencymultiplier="1" sineamplitudemultiplier="1" blinkfrequency="0" blinkdurationin="0.2" blinkdurationout="0.5" blinkholdtime="0" blinkrotationin="0" blinkrotationout="45" blinkforce="50" blinktransitionin="Linear" blinktransitionout="Linear" inheritlimbdepth="None" onlyblinkinwater="False">
    <deformablesprite texture="" sourcerect="764,88,163,68" origin="0.4592154,0.62377936" depth="0" color="255,255,255,255" deadcolor="255,255,255,255" deadcolortime="0" subdivisions="3,3" ignoretint="False">
      <spritedeformation type="bendjoint" resolution="3,3" sync="-1" typename="bendjoint" blendmode="Add" usemovementsine="False" stopwhenhostisdead="False" sineoffset="0" maxrotation="20" strength="1" onlyinwater="False" />
    </deformablesprite>
    <damagemodifier damagesound="" damagemultiplier="0.1" probabilitymultiplier="1" armorsector="0,360" deflectprojectiles="False" afflictionidentifiers="" afflictiontypes="damage" damageparticle="" />
  </limb>
  <limb id="13" radius="22.525" width="164.29999" height="0" name="Limb 13" type="None" spriteorientation="NaN" flip="True" mirrorvertically="False" mirrorhorizontally="False" hide="False" attackpriority="1" steerforce="0" density="9" ignorecollisions="False" angulardamping="7" pullpos="0,0" stepoffset="0,0" refjoint="-1" mouthpos="0,0" notes="" constanttorque="0" constantangle="0" scale="1" attackforcemultiplier="1" minseverancedamage="1" healthindex="0" friction="0.3" restitution="0.05" severedfadeouttime="10" applytailangle="False" sinefrequencymultiplier="1" sineamplitudemultiplier="1" blinkfrequency="0" blinkdurationin="0.2" blinkdurationout="0.5" blinkholdtime="0" blinkrotationin="0" blinkrotationout="45" blinkforce="50" blinktransitionin="Linear" blinktransitionout="Linear" inheritlimbdepth="None" onlyblinkinwater="False">
    <sprite texture="" sourcerect="556,74,211,53" origin="0.5,0.5" depth="0" color="255,255,255,255" deadcolor="255,255,255,255" deadcolortime="0" ignoretint="False" />
  </limb>
  <limb id="14" radius="21.650002" width="153.75002" height="0" name="Limb 14" type="None" spriteorientation="NaN" flip="True" mirrorvertically="False" mirrorhorizontally="False" hide="False" attackpriority="1" steerforce="0" density="9" ignorecollisions="False" angulardamping="7" pullpos="0,0" stepoffset="0,0" refjoint="-1" mouthpos="0,0" notes="" constanttorque="0" constantangle="0" scale="1" attackforcemultiplier="1" minseverancedamage="1" healthindex="0" friction="0.3" restitution="0.05" severedfadeouttime="10" applytailangle="False" sinefrequencymultiplier="1" sineamplitudemultiplier="1" blinkfrequency="0" blinkdurationin="0.2" blinkdurationout="0.5" blinkholdtime="0" blinkrotationin="0" blinkrotationout="45" blinkforce="50" blinktransitionin="Linear" blinktransitionout="Linear" inheritlimbdepth="None" onlyblinkinwater="False">
    <sprite texture="" sourcerect="387,84,173,98" origin="0.5,0.5" depth="0" color="255,255,255,255" deadcolor="255,255,255,255" deadcolortime="0" ignoretint="False" />
  </limb>
  <limb id="15" radius="60.775" width="0" height="0" name="Limb 15" type="None" spriteorientation="NaN" flip="True" mirrorvertically="False" mirrorhorizontally="False" hide="False" attackpriority="1" steerforce="0" density="7" ignorecollisions="False" angulardamping="7" pullpos="0,0" stepoffset="0,0" refjoint="-1" mouthpos="0,0" notes="" constanttorque="0" constantangle="0" scale="1" attackforcemultiplier="1" minseverancedamage="1" healthindex="0" friction="0.3" restitution="0.05" severedfadeouttime="10" applytailangle="False" sinefrequencymultiplier="1" sineamplitudemultiplier="1" blinkfrequency="0" blinkdurationin="0.2" blinkdurationout="0.5" blinkholdtime="0" blinkrotationin="0" blinkrotationout="45" blinkforce="50" blinktransitionin="Linear" blinktransitionout="Linear" inheritlimbdepth="None" onlyblinkinwater="False">
    <sprite texture="" sourcerect="256,38,135,143" origin="0.5,0.5" depth="0" color="255,255,255,255" deadcolor="255,255,255,255" deadcolortime="0" ignoretint="False" />
    <lightsource color="255,100,0,255" range="1160" scale="1" offset="0,0" rotation="0" flicker="0" flickerspeed="1" pulsefrequency="0" pulseamount="0" blinkfrequency="0">
      <lighttexture texture="Content/Lights/light.png" origin="0.52,0.52" size="1,1" />
    </lightsource>
    <attack structuresoundtype="StructureBlunt" context="Any" targettype="Any" targetlimbtype="None" hitdetectiontype="Distance" afterattack="FallBack" afterattackdelay="0" reverse="False" retreat="False" range="100" damagerange="150" duration="0.15" cooldown="10" secondarycooldown="0" cooldownrandomfactor="0" structuredamage="300" itemdamage="80" stun="0" onlyhumans="False" applyforceonlimbs="" force="20" rootforceworldstart="0,0" rootforceworldmiddle="0,0" rootforceworldend="0,0" roottransitioneasing="Linear" torque="0" applyforcesonlyonce="False" targetimpulse="500" targetimpulseworld="0,0" targetforce="0" targetforceworld="0,0" severlimbsprobability="0" priority="0" fullspeedafterattack="False" penetration="0" levelwalldamage="300" ranged="False" avoidfriendlyfire="False" requiredangle="20" submarineimpactmultiplier="1" blink="False">
      <affliction identifier="lacerations" strength="60" probability="1" />
      <affliction identifier="burn" strength="20" probability="1" />
    </attack>
  </limb>
  <joint name="Joint 0 - 1" limb1="1" limb2="0" limb1anchor="-146.22948,-0.57636666" limb2anchor="89.21793,-1.9006732" canbesevered="True" severanceprobabilitymodifier="0" breaksound="gore" limitenabled="True" upperlimit="11" lowerlimit="-12.000014" stiffness="0.25" scale="1" weldjoint="False" clockwiserotation="False" />
  <joint limb1="7" limb2="11" limb1anchor="-100.54156,71.944016" limb2anchor="106.898094,4.7410803" name="Joint 7 - 11" canbesevered="True" severanceprobabilitymodifier="0.01" breaksound="gore" limitenabled="True" upperlimit="6" lowerlimit="-6.0000205" stiffness="0.25" scale="1" weldjoint="False" clockwiserotation="False" />
  <joint limb1="11" limb2="12" limb1anchor="-133.13689,-17.080988" limb2anchor="84.62192,-7.9060845" name="Joint 11 - 12" canbesevered="True" severanceprobabilitymodifier="0" breaksound="gore" limitenabled="True" upperlimit="5" lowerlimit="-24" stiffness="0.25" scale="1" weldjoint="False" clockwiserotation="False" />
  <joint limb1="8" limb2="9" limb1anchor="-81.11187,-69.36109" limb2anchor="140.40291,-3.4443974" name="Joint 8 - 9" canbesevered="True" severanceprobabilitymodifier="0.2" breaksound="gore" limitenabled="True" upperlimit="8" lowerlimit="-6.0000205" stiffness="0.25" scale="1" weldjoint="False" clockwiserotation="False" />
  <joint limb1="9" limb2="10" limb1anchor="-147.5628,16.306845" limb2anchor="122.09589,7.7526174" name="Joint 9 - 10" canbesevered="True" severanceprobabilitymodifier="0.3" breaksound="gore" limitenabled="True" upperlimit="11" lowerlimit="-9.999998" stiffness="0.25" scale="1" weldjoint="False" clockwiserotation="False" />
  <joint limb1="1" limb2="7" limb1anchor="-26.211086,45.429646" limb2anchor="43.28758,-3.9304938" name="Joint 1 - 7" canbesevered="True" severanceprobabilitymodifier="0.1" breaksound="gore" limitenabled="True" upperlimit="0" lowerlimit="0" stiffness="0.25" scale="1" weldjoint="False" clockwiserotation="False" />
  <joint limb1="1" limb2="8" limb1anchor="54.76266,2.8434358" limb2anchor="34.253838,24.68593" name="Joint 1 - 8" canbesevered="True" severanceprobabilitymodifier="0.1" breaksound="gore" limitenabled="True" upperlimit="10" lowerlimit="10" stiffness="0.25" scale="1" weldjoint="False" clockwiserotation="False" />
  <joint limb1="0" limb2="2" limb1anchor="-88.29202,-3.3929892" limb2anchor="86.061455,-3.9427426" name="Joint 0 - 2" canbesevered="True" severanceprobabilitymodifier="0" breaksound="gore" limitenabled="True" upperlimit="17" lowerlimit="-18.000008" stiffness="0.25" scale="1" weldjoint="False" clockwiserotation="False" />
  <joint limb1="2" limb2="3" limb1anchor="-85.53413,7.6684847" limb2anchor="83.84127,-0.540293" name="Joint 2 - 3" canbesevered="True" severanceprobabilitymodifier="0" breaksound="gore" limitenabled="True" upperlimit="14" lowerlimit="-16.00002" stiffness="0.25" scale="1" weldjoint="False" clockwiserotation="False" />
  <joint limb1="3" limb2="4" limb1anchor="-90.590576,-4.5531187" limb2anchor="99.943474,-10.762097" name="Joint 3 - 4" canbesevered="True" severanceprobabilitymodifier="0" breaksound="gore" limitenabled="True" upperlimit="14" lowerlimit="-12.000014" stiffness="0.25" scale="1" weldjoint="False" clockwiserotation="False" />
  <joint limb1="4" limb2="5" limb1anchor="-87.7302,12.857544" limb2anchor="56.78698,6.0859404" name="Joint 4 - 5" canbesevered="True" severanceprobabilitymodifier="0" breaksound="gore" limitenabled="True" upperlimit="14" lowerlimit="-14.000003" stiffness="0.25" scale="1" weldjoint="False" clockwiserotation="False" />
  <joint limb1="5" limb2="6" limb1anchor="-57.340286,-5.038271" limb2anchor="66.70782,0.045830384" name="Joint 5 - 6" canbesevered="True" severanceprobabilitymodifier="0" breaksound="gore" limitenabled="True" upperlimit="13" lowerlimit="-16.00002" stiffness="0.25" scale="1" weldjoint="False" clockwiserotation="False" />
  <joint limb1="12" limb2="13" limb1anchor="-68.417465,14.45362" limb2anchor="99.77432,-12.738937" name="Joint 12 - 13" canbesevered="True" severanceprobabilitymodifier="0" breaksound="gore" limitenabled="True" upperlimit="5" lowerlimit="-30.000021" stiffness="0.25" scale="1" weldjoint="False" clockwiserotation="False" />
  <joint limb1="13" limb2="14" limb1anchor="-99.165184,0" limb2anchor="87.21,32.39" name="Joint 13 - 14" canbesevered="True" severanceprobabilitymodifier="0" breaksound="gore" limitenabled="True" upperlimit="12" lowerlimit="-32.00001" stiffness="0.25" scale="1" weldjoint="False" clockwiserotation="False" />
  <joint limb1="14" limb2="15" limb1anchor="-82.23,-12.46" limb2anchor="67.28,-34.88" name="Joint 14 - 15" canbesevered="True" severanceprobabilitymodifier="0" breaksound="gore" limitenabled="True" upperlimit="0" lowerlimit="0" stiffness="0.25" scale="1" weldjoint="False" clockwiserotation="False" />
</Ragdoll>