<?xml version="1.0" encoding="utf-8"?>
<Ragdoll type="Bruteflora" texture="%ModDir%/Characters/XanmonsterCreatures/Bruteflora/bruteflora.png" canentersubmarine="True" canwalk="True" spritesheetorientation="0" limbscale="1.075" jointscale="1.075" texturescale="1" colliderheightfromfloor="95" impacttolerance="50" draggable="True" mainlimb="Head" color="255,255,255,255">
  <collider radius="15" width="1" name="Main Collider" height="55" />
  <collider radius="15" width="1" name="Secondary Collider" height="60" />
  <limb id="0" name="Limb 0" type="Torso" height="232.05002" width="202.3" notes="" spriteorientation="NaN" flip="True" mirrorvertically="False" mirrorhorizontally="False" hide="False" attackpriority="1" steerforce="0" radius="0" density="10" ignorecollisions="False" angulardamping="7" pullpos="0,0" stepoffset="0,0" refjoint="-1" mouthpos="0,0" constanttorque="0" constantangle="0" scale="0.277" attackforcemultiplier="1" healthindex="0" friction="0.3" restitution="0.05" minseverancedamage="1" severedfadeouttime="10" applytailangle="False" sinefrequencymultiplier="1" sineamplitudemultiplier="1" blinkfrequency="0" blinkdurationin="0.2" blinkdurationout="0.5" blinkholdtime="0" blinkrotationin="0" blinkrotationout="45" blinkforce="50" blinktransitionin="Linear" blinktransitionout="Linear" inheritlimbdepth="None" onlyblinkinwater="False">
    <sprite texture="" sourcerect="450,194,231,261" origin="0.5151515,0.5229885" depth="0.3" color="255,255,255,255" deadcolor="255,255,255,255" deadcolortime="0" ignoretint="False" />
    <damagemodifier damagesound="" damagemultiplier="10" probabilitymultiplier="1" armorsector="0,360" deflectprojectiles="False" afflictionidentifiers="burn" afflictiontypes="" damageparticle="" />
  </limb>
  <limb id="1" name="Limb 1" type="Head" height="111.35" width="137.70001" notes="" spriteorientation="NaN" flip="True" mirrorvertically="False" mirrorhorizontally="False" hide="False" attackpriority="1" steerforce="0" radius="0" density="10" ignorecollisions="True" angulardamping="7" pullpos="0,0" stepoffset="0,0" refjoint="-1" mouthpos="0,0" constanttorque="0" constantangle="0" scale="0.277" attackforcemultiplier="1" healthindex="0" friction="0.3" restitution="0.05" minseverancedamage="1" severedfadeouttime="10" applytailangle="False" sinefrequencymultiplier="1" sineamplitudemultiplier="1" blinkfrequency="0" blinkdurationin="0.2" blinkdurationout="0.5" blinkholdtime="0" blinkrotationin="0" blinkrotationout="45" blinkforce="50" blinktransitionin="Linear" blinktransitionout="Linear" inheritlimbdepth="None" onlyblinkinwater="False">
    <sprite texture="" sourcerect="153,10,162,131" origin="0.7328452,0.49052772" depth="0.9000001" color="255,255,255,255" deadcolor="255,255,255,255" deadcolortime="0" ignoretint="False" />
    <lightsource color="10,0,219,255" range="100" scale="0.277" offset="0,0" rotation="0" flicker="0" flickerspeed="1" pulsefrequency="0" pulseamount="0" blinkfrequency="0">
      <lighttexture texture="Content/Lights/lightcone.png" origin="0,0.5" size="1,1" />
    </lightsource>
  </limb>
  <limb id="2" name="Limb 2" type="LeftArm" height="129.20001" width="135.15" notes="" spriteorientation="NaN" flip="True" mirrorvertically="False" mirrorhorizontally="False" hide="False" attackpriority="1" steerforce="0" radius="0" density="10" ignorecollisions="False" angulardamping="7" pullpos="0,0" stepoffset="0,0" refjoint="-1" mouthpos="0,0" constanttorque="0" constantangle="0" scale="0.277" attackforcemultiplier="1" healthindex="0" friction="0.3" restitution="0.05" minseverancedamage="1" severedfadeouttime="10" applytailangle="False" sinefrequencymultiplier="1" sineamplitudemultiplier="1" blinkfrequency="0" blinkdurationin="0.2" blinkdurationout="0.5" blinkholdtime="0" blinkrotationin="0" blinkrotationout="45" blinkforce="50" blinktransitionin="Linear" blinktransitionout="Linear" inheritlimbdepth="None" onlyblinkinwater="False">
    <sprite texture="" sourcerect="278,180,159,152" origin="0.5,0.5" depth="0.10000002" color="255,255,255,255" deadcolor="255,255,255,255" deadcolortime="0" ignoretint="False" />
  </limb>
  <limb id="3" name="Limb 3" type="LeftHand" height="125.80001" width="135.99998" notes="" spriteorientation="NaN" flip="True" mirrorvertically="False" mirrorhorizontally="False" hide="False" attackpriority="1" steerforce="0" radius="0" density="10" ignorecollisions="False" angulardamping="7" pullpos="0,0" stepoffset="0,0" refjoint="-1" mouthpos="0,0" constanttorque="0" constantangle="0" scale="0.277" attackforcemultiplier="1" healthindex="0" friction="0.3" restitution="0.05" minseverancedamage="1" severedfadeouttime="10" applytailangle="False" sinefrequencymultiplier="1" sineamplitudemultiplier="1" blinkfrequency="0" blinkdurationin="0.2" blinkdurationout="0.5" blinkholdtime="0" blinkrotationin="0" blinkrotationout="45" blinkforce="50" blinktransitionin="Linear" blinktransitionout="Linear" inheritlimbdepth="None" onlyblinkinwater="False">
    <sprite texture="" sourcerect="285,330,160,148" origin="0.5,0.5" depth="0.10000002" color="255,255,255,255" deadcolor="255,255,255,255" deadcolortime="0" ignoretint="False" />
    <attack structuresoundtype="StructureBlunt" context="Any" targettype="Any" targetlimbtype="None" hitdetectiontype="Distance" afterattack="Pursue" afterattackdelay="0" reverse="False" retreat="False" range="100" damagerange="100" duration="0.25" cooldown="5" secondarycooldown="0" cooldownrandomfactor="0" structuredamage="10" itemdamage="0" stun="0" onlyhumans="False" applyforceonlimbs="" force="10" rootforceworldstart="0,0" rootforceworldmiddle="0,0" rootforceworldend="0,0" roottransitioneasing="Linear" torque="0" applyforcesonlyonce="False" targetimpulse="10" targetimpulseworld="0,0" targetforce="2" targetforceworld="0,0" severlimbsprobability="0" priority="0" fullspeedafterattack="False" penetration="0" levelwalldamage="10" ranged="False" avoidfriendlyfire="False" requiredangle="20" submarineimpactmultiplier="1" blink="False">
      <affliction identifier="internaldamage" strength="15" probability="1" />
      <affliction identifier="stun" strength="0.2" probability="1" />
    </attack>
  </limb>
  <limb id="4" name="Limb 4" type="RightArm" height="160.65001" width="122.40001" notes="" spriteorientation="NaN" flip="True" mirrorvertically="False" mirrorhorizontally="False" hide="False" attackpriority="1" steerforce="0" radius="0" density="10" ignorecollisions="False" angulardamping="7" pullpos="0,0" stepoffset="0,0" refjoint="-1" mouthpos="0,0" constanttorque="0" constantangle="0" scale="0.277" attackforcemultiplier="1" healthindex="0" friction="0.3" restitution="0.05" minseverancedamage="1" severedfadeouttime="10" applytailangle="False" sinefrequencymultiplier="1" sineamplitudemultiplier="1" blinkfrequency="0" blinkdurationin="0.2" blinkdurationout="0.5" blinkholdtime="0" blinkrotationin="0" blinkrotationout="45" blinkforce="50" blinktransitionin="Linear" blinktransitionout="Linear" inheritlimbdepth="None" onlyblinkinwater="False">
    <sprite texture="" sourcerect="757,199,144,189" origin="0.5,0.5" depth="1" color="255,255,255,255" deadcolor="255,255,255,255" deadcolortime="0" ignoretint="False" />
  </limb>
  <limb id="5" name="Limb 5" type="RightHand" height="153.84999" width="110.5" notes="" spriteorientation="NaN" flip="True" mirrorvertically="False" mirrorhorizontally="False" hide="False" attackpriority="1" steerforce="0" radius="0" density="10" ignorecollisions="False" angulardamping="7" pullpos="0,0" stepoffset="0,0" refjoint="-1" mouthpos="0,0" constanttorque="0" constantangle="0" scale="0.277" attackforcemultiplier="1" healthindex="0" friction="0.3" restitution="0.05" minseverancedamage="1" severedfadeouttime="10" applytailangle="False" sinefrequencymultiplier="1" sineamplitudemultiplier="1" blinkfrequency="0" blinkdurationin="0.2" blinkdurationout="0.5" blinkholdtime="0" blinkrotationin="0" blinkrotationout="45" blinkforce="50" blinktransitionin="Linear" blinktransitionout="Linear" inheritlimbdepth="None" onlyblinkinwater="False">
    <sprite texture="" sourcerect="808,383,130,181" origin="0.5,0.5" depth="1" color="255,255,255,255" deadcolor="255,255,255,255" deadcolortime="0" ignoretint="False" />
  </limb>
  <limb id="6" name="Limb 6" type="LeftThigh" height="153" width="98.59999" notes="" spriteorientation="NaN" flip="True" mirrorvertically="False" mirrorhorizontally="False" hide="False" attackpriority="1" steerforce="0" radius="0" density="10" ignorecollisions="False" angulardamping="7" pullpos="0,0" stepoffset="0,0" refjoint="-1" mouthpos="0,0" constanttorque="0" constantangle="0" scale="0.277" attackforcemultiplier="1" healthindex="0" friction="0.3" restitution="0.05" minseverancedamage="1" severedfadeouttime="10" applytailangle="False" sinefrequencymultiplier="1" sineamplitudemultiplier="1" blinkfrequency="0" blinkdurationin="0.2" blinkdurationout="0.5" blinkholdtime="0" blinkrotationin="0" blinkrotationout="45" blinkforce="50" blinktransitionin="Linear" blinktransitionout="Linear" inheritlimbdepth="None" onlyblinkinwater="False">
    <sprite texture="" sourcerect="749,577,116,180" origin="0.5,0.5" depth="0.6" color="255,255,255,255" deadcolor="255,255,255,255" deadcolortime="0" ignoretint="False" />
  </limb>
  <limb id="7" name="Limb 7" type="LeftLeg" height="113.049995" width="119.84999" notes="" spriteorientation="NaN" flip="True" mirrorvertically="False" mirrorhorizontally="False" hide="False" attackpriority="1" steerforce="0" radius="0" density="10" ignorecollisions="False" angulardamping="7" pullpos="0,0" stepoffset="0,0" refjoint="-1" mouthpos="0,0" constanttorque="0" constantangle="0" scale="0.277" attackforcemultiplier="1" healthindex="0" friction="0.3" restitution="0.05" minseverancedamage="1" severedfadeouttime="10" applytailangle="False" sinefrequencymultiplier="1" sineamplitudemultiplier="1" blinkfrequency="0" blinkdurationin="0.2" blinkdurationout="0.5" blinkholdtime="0" blinkrotationin="0" blinkrotationout="45" blinkforce="50" blinktransitionin="Linear" blinktransitionout="Linear" inheritlimbdepth="None" onlyblinkinwater="False">
    <sprite texture="" sourcerect="724,754,141,133" origin="0.5,0.5" depth="0.2" color="255,255,255,255" deadcolor="255,255,255,255" deadcolortime="0" ignoretint="False" />
  </limb>
  <limb id="8" name="Limb 8" type="LeftFoot" height="67.99999" width="164.04999" notes="" spriteorientation="NaN" flip="True" mirrorvertically="False" mirrorhorizontally="False" hide="False" attackpriority="1" steerforce="0" radius="0" density="10" ignorecollisions="False" angulardamping="7" pullpos="0,0" stepoffset="0,0" refjoint="-1" mouthpos="0,0" constanttorque="0" constantangle="0" scale="0.277" attackforcemultiplier="1" healthindex="0" friction="0.3" restitution="0.05" minseverancedamage="1" severedfadeouttime="10" applytailangle="False" sinefrequencymultiplier="1" sineamplitudemultiplier="1" blinkfrequency="0" blinkdurationin="0.2" blinkdurationout="0.5" blinkholdtime="0" blinkrotationin="0" blinkrotationout="45" blinkforce="50" blinktransitionin="Linear" blinktransitionout="Linear" inheritlimbdepth="None" onlyblinkinwater="False">
    <sprite texture="" sourcerect="690,884,193,80" origin="0.5,0.5" depth="0.2" color="255,255,255,255" deadcolor="255,255,255,255" deadcolortime="0" ignoretint="False" />
    <sound tag="footstep_armor_heavy" />
  </limb>
  <limb id="9" name="Limb 9" type="RightThigh" height="169.15001" width="81.6" notes="" spriteorientation="NaN" flip="True" mirrorvertically="False" mirrorhorizontally="False" hide="False" attackpriority="1" steerforce="0" radius="0" density="10" ignorecollisions="False" angulardamping="7" pullpos="0,0" stepoffset="0,0" refjoint="-1" mouthpos="0,0" constanttorque="0" constantangle="0" scale="0.277" attackforcemultiplier="1" healthindex="0" friction="0.3" restitution="0.05" minseverancedamage="1" severedfadeouttime="10" applytailangle="False" sinefrequencymultiplier="1" sineamplitudemultiplier="1" blinkfrequency="0" blinkdurationin="0.2" blinkdurationout="0.5" blinkholdtime="0" blinkrotationin="0" blinkrotationout="45" blinkforce="50" blinktransitionin="Linear" blinktransitionout="Linear" inheritlimbdepth="None" onlyblinkinwater="False">
    <sprite texture="" sourcerect="356,553,96,199" origin="0.5,0.5" depth="0.2" color="255,255,255,255" deadcolor="255,255,255,255" deadcolortime="0" ignoretint="False" />
  </limb>
  <limb id="10" name="Limb 10" type="RightLeg" height="108.8" width="106.25" notes="" spriteorientation="NaN" flip="True" mirrorvertically="False" mirrorhorizontally="False" hide="False" attackpriority="1" steerforce="0" radius="0" density="10" ignorecollisions="False" angulardamping="7" pullpos="0,0" stepoffset="0,0" refjoint="-1" mouthpos="0,0" constanttorque="0" constantangle="0" scale="0.277" attackforcemultiplier="1" healthindex="0" friction="0.3" restitution="0.05" minseverancedamage="1" severedfadeouttime="10" applytailangle="False" sinefrequencymultiplier="1" sineamplitudemultiplier="1" blinkfrequency="0" blinkdurationin="0.2" blinkdurationout="0.5" blinkholdtime="0" blinkrotationin="0" blinkrotationout="45" blinkforce="50" blinktransitionin="Linear" blinktransitionout="Linear" inheritlimbdepth="None" onlyblinkinwater="False">
    <sprite texture="" sourcerect="332,751,125,128" origin="0.5,0.5" depth="0.1" color="255,255,255,255" deadcolor="255,255,255,255" deadcolortime="0" ignoretint="False" />
    <attack structuresoundtype="StructureBlunt" context="Any" targettype="Any" targetlimbtype="None" hitdetectiontype="Distance" afterattack="FollowThrough" afterattackdelay="5" reverse="False" retreat="False" range="100" damagerange="100" duration="0.1" cooldown="5" secondarycooldown="0" cooldownrandomfactor="0" structuredamage="10" itemdamage="0" stun="0" onlyhumans="False" applyforceonlimbs="9" force="9.999981" rootforceworldstart="0,0" rootforceworldmiddle="0,0" rootforceworldend="0,0" roottransitioneasing="Linear" torque="0" applyforcesonlyonce="False" targetimpulse="100" targetimpulseworld="0,0" targetforce="10" targetforceworld="0,0" severlimbsprobability="0" priority="0" fullspeedafterattack="False" penetration="0" levelwalldamage="10" ranged="False" avoidfriendlyfire="False" requiredangle="20" submarineimpactmultiplier="1" blink="False">
      <affliction identifier="internaldamage" strength="20" probability="1" />
      <affliction identifier="stun" strength="1" probability="1" />
    </attack>
  </limb>
  <limb id="11" name="Limb 11" type="RightFoot" height="63.75" width="140.24998" notes="" spriteorientation="NaN" flip="True" mirrorvertically="False" mirrorhorizontally="False" hide="False" attackpriority="1" steerforce="0" radius="0" density="10" ignorecollisions="False" angulardamping="7" pullpos="0,0" stepoffset="0,0" refjoint="-1" mouthpos="0,0" constanttorque="0" constantangle="0" scale="0.277" attackforcemultiplier="1" healthindex="0" friction="0.3" restitution="0.05" minseverancedamage="1" severedfadeouttime="10" applytailangle="False" sinefrequencymultiplier="1" sineamplitudemultiplier="1" blinkfrequency="0" blinkdurationin="0.2" blinkdurationout="0.5" blinkholdtime="0" blinkrotationin="0" blinkrotationout="45" blinkforce="50" blinktransitionin="Linear" blinktransitionout="Linear" inheritlimbdepth="None" onlyblinkinwater="False">
    <sprite texture="" sourcerect="312,875,165,75" origin="0.5,0.5" depth="0.1" color="255,255,255,255" deadcolor="255,255,255,255" deadcolortime="0" ignoretint="False" />
    <sound tag="footstep_armor_heavy" />
  </limb>
  <limb id="12" name="Limb 12" type="Waist" height="0" width="0" notes="" spriteorientation="NaN" flip="True" mirrorvertically="False" mirrorhorizontally="False" hide="False" attackpriority="1" steerforce="0" radius="80" density="10" ignorecollisions="False" angulardamping="7" pullpos="0,0" stepoffset="0,0" refjoint="-1" mouthpos="0,0" constanttorque="0" constantangle="0" scale="0.277" attackforcemultiplier="1" healthindex="0" friction="0.3" restitution="0.05" minseverancedamage="1" severedfadeouttime="10" applytailangle="False" sinefrequencymultiplier="1" sineamplitudemultiplier="1" blinkfrequency="0" blinkdurationin="0.2" blinkdurationout="0.5" blinkholdtime="0" blinkrotationin="0" blinkrotationout="45" blinkforce="50" blinktransitionin="Linear" blinktransitionout="Linear" inheritlimbdepth="None" onlyblinkinwater="False">
    <sprite texture="" sourcerect="494,501,185,139" origin="0.537837,0.47122324" depth="0.29999992" color="255,255,255,255" deadcolor="255,255,255,255" deadcolortime="0" ignoretint="False" />
  </limb>
  <joint limb1="1" limb2="0" limb1anchor="-81.682846,-11.19153" limb2anchor="-19.446287,114.67047" name="Joint 1 - 0" canbesevered="True" limitenabled="True" upperlimit="10" lowerlimit="0" stiffness="0.25" scale="0.277" severanceprobabilitymodifier="0" breaksound="" weldjoint="False" clockwiserotation="False" />
  <joint limb1="0" limb2="12" limb1anchor="-25.698284,-84.244415" limb2anchor="-5.831198,39.54874" name="Joint 0 - 12" canbesevered="True" limitenabled="True" upperlimit="0" lowerlimit="0" stiffness="0.2" scale="0.277" severanceprobabilitymodifier="0.1" breaksound="" weldjoint="False" clockwiserotation="False" />
  <joint limb1="12" limb2="6" limb1anchor="59.06111,-18.436619" limb2anchor="-13,63" name="Joint 12 - 6" canbesevered="True" limitenabled="True" upperlimit="24" lowerlimit="-12" stiffness="0.25" scale="0.277" severanceprobabilitymodifier="0.1" breaksound="" weldjoint="False" clockwiserotation="False" />
  <joint limb1="12" limb2="9" limb1anchor="-19.11885,-6.1998005" limb2anchor="-2.820456,83.2905" name="Joint 12 - 9" canbesevered="True" limitenabled="True" upperlimit="58" lowerlimit="-12" stiffness="0.25" scale="0.277" severanceprobabilitymodifier="0.1" breaksound="" weldjoint="False" clockwiserotation="False" />
  <joint limb1="9" limb2="10" limb1anchor="-0.6679057,-80.31206" limb2anchor="8.3351345,69.775955" name="Joint 9 - 10" canbesevered="True" limitenabled="True" upperlimit="0" lowerlimit="-100" stiffness="0.25" scale="0.277" severanceprobabilitymodifier="0.1" breaksound="" weldjoint="False" clockwiserotation="False" />
  <joint limb1="6" limb2="7" limb1anchor="4.4213934,-88.59149" limb2anchor="15.0391655,64.15535" name="Joint 6 - 7" canbesevered="True" limitenabled="True" upperlimit="0" lowerlimit="-100" stiffness="0.25" scale="0.277" severanceprobabilitymodifier="0.1" breaksound="" weldjoint="False" clockwiserotation="False" />
  <joint limb1="10" limb2="11" limb1anchor="-8.059445,-59.170555" limb2anchor="-7.067536,38.20353" name="Joint 10 - 11" canbesevered="True" limitenabled="True" upperlimit="0" lowerlimit="0" stiffness="0.25" scale="0.277" severanceprobabilitymodifier="0" breaksound="gore" weldjoint="False" clockwiserotation="False" />
  <joint limb1="7" limb2="8" limb1anchor="-8.830866,-63.96996" limb2anchor="3.995014,38.417976" name="Joint 7 - 8" canbesevered="True" limitenabled="True" upperlimit="0" lowerlimit="0" stiffness="0.25" scale="0.277" severanceprobabilitymodifier="0" breaksound="gore" weldjoint="False" clockwiserotation="False" />
  <joint limb1="2" limb2="0" limb1anchor="39.991196,13.145694" limb2anchor="-42.661083,65.951744" name="Joint 2 - 0" canbesevered="True" limitenabled="True" upperlimit="120" lowerlimit="-157.00002" stiffness="0.25" scale="0.277" severanceprobabilitymodifier="0.1" breaksound="" weldjoint="False" clockwiserotation="False" />
  <joint limb1="5" limb2="4" limb1anchor="-17.849976,85.3663" limb2anchor="27.69671,-94.12121" name="Joint 5 - 4" canbesevered="True" limitenabled="True" upperlimit="2" lowerlimit="-4.999999" stiffness="0.25" scale="0.277" severanceprobabilitymodifier="0" breaksound="gore" weldjoint="False" clockwiserotation="False" />
  <joint limb1="3" limb2="2" limb1anchor="-21.773247,72.918755" limb2anchor="-18.013689,-74.584625" name="Joint 3 - 2" canbesevered="True" limitenabled="True" upperlimit="0" lowerlimit="-60" stiffness="0.2" scale="0.277" severanceprobabilitymodifier="0" breaksound="gore" weldjoint="False" clockwiserotation="False" />
  <joint limb1="4" limb2="0" limb1anchor="-43.796623,47.26" limb2anchor="-32.07,59.07" name="Joint 4 - 0" canbesevered="True" severanceprobabilitymodifier="0.1" breaksound="" limitenabled="True" upperlimit="46" lowerlimit="0" stiffness="0.25" scale="0.277" weldjoint="False" clockwiserotation="False" />
</Ragdoll>